baler_compressor/__init__.py
baler_compressor/compressor.py
baler_compressor/config.py
baler_compressor/data_processing.py
baler_compressor/decompressor.py
baler_compressor/helper.py
baler_compressor/legacy_models.py
baler_compressor/trainer.py
baler_compressor/utils.py
baler_compressor-0.0.6.dist-info/METADATA
baler_compressor-0.0.6.dist-info/WHEEL
baler_compressor-0.0.6.dist-info/licenses/LICENSE
baler_compressor-0.0.6.dist-info/licenses/NOTICE
baler_compressor-0.0.6.dist-info/RECORD
