Metadata-Version: 2.1
Name: baler-compressor
Version: 0.0.6
Summary: Machine Learning Based Data Compression
Project-URL: Homepage, https://github.com/baler-collaboration/baler
Project-URL: Issues, https://github.com/baler-collaboration/baler/issues
Author-email: Alexander Ekman <alexander.ekman@fysik.lu.se>
License-File: LICENSE
License-File: NOTICE
Classifier: License :: OSI Approved :: Apache Software License
Classifier: Operating System :: OS Independent
Classifier: Programming Language :: Python :: 3
Requires-Python: >=3.8
